LICENSE
README.md
setup.py
deadbear_fib_py/__init__.py
deadbear_fib_py/version.py
deadbear_fib_py.egg-info/PKG-INFO
deadbear_fib_py.egg-info/SOURCES.txt
deadbear_fib_py.egg-info/dependency_links.txt
deadbear_fib_py.egg-info/entry_points.txt
deadbear_fib_py.egg-info/requires.txt
deadbear_fib_py.egg-info/top_level.txt
deadbear_fib_py/cmd/__init__.py
deadbear_fib_py/cmd/fib_numb.py
deadbear_fib_py/fib_calcs/__init__.py
deadbear_fib_py/fib_calcs/fib_number.py
deadbear_fib_py/fib_calcs/fib_numbers.py
tests/deadbear_fib_py/__init__.py
tests/deadbear_fib_py/fib_calcs/__init__.py
tests/deadbear_fib_py/fib_calcs/test_fib_number.py
tests/deadbear_fib_py/fib_calcs/test_fib_numbers.py